pyjne_peru/__init__.py
pyjne_peru/client.py
pyjne_peru/entities.py
pyjne_peru/error.py
pyjne_peru/parsers.py
pyjne_peru/utils.py
python_jne_peru-0.1.0.dist-info/AUTHORS.rst
python_jne_peru-0.1.0.dist-info/LICENSE
python_jne_peru-0.1.0.dist-info/METADATA
python_jne_peru-0.1.0.dist-info/WHEEL
python_jne_peru-0.1.0.dist-info/top_level.txt
python_jne_peru-0.1.0.dist-info/RECORD
